<?xml version="1.0" encoding="UTF-8"?> 
 <definitions 
 xmlns="http://schemas.xmlsoap.org/wsdl/" 
 xmlns:wsdl="http://schemas.xmlsoap.org/wsdl/" 
 xmlns:xsd="http://www.w3.org/2001/XMLSchema" 
 xmlns:soap="http://schemas.xmlsoap.org/wsdl/soap/" name="BankAccountService" targetNamespace="http://service.bank/" xmlns:tns="http://service.bank/" 
 >
    <wsdl:message name="getBalance"/>
    <wsdl:message name="getBalanceResponse"/>
    <wsdl:message name="deposit"/>
    <wsdl:message name="depositResponse"/>
    <wsdl:portType name="BankAccount">
        <wsdl:operation name="getBalance">
            <wsdl:input message="tns:getBalance"/>
            <wsdl:output message="tns:getBalanceResponse"/>
        </wsdl:operation>
        <wsdl:operation name="deposit">
            <wsdl:input message="tns:deposit"/>
            <wsdl:output message="tns:depositResponse"/>
        </wsdl:operation>
    </wsdl:portType>
    <wsdl:binding name="BankAccountPortBinding" type="tns:BankAccount">
        <wsdl:operation name="getBalance">
            <wsdl:input/>
            <wsdl:output/>
        </wsdl:operation>
        <wsdl:operation name="deposit">
            <wsdl:input/>
            <wsdl:output/>
        </wsdl:operation>
    </wsdl:binding>
    <wsdl:service name="BankAccountService">
        <wsdl:port name="BankAccountPort" binding="tns:BankAccountPortBinding"/>
    </wsdl:service>
</definitions>
